regioinvent/__init__.py
regioinvent/main.py
regioinvent/data/EF/EF31_regionalized-for-ecoinvent-v310.87ec66ed7e5775d0132d1129fb5caf03.bw2package
regioinvent/data/EF/EF31_regionalized-for-ecoinvent-v39.ff0965b0f9793fbd2a351c9155946122.bw2package
regioinvent/data/IW/impact_world_plus_21_regionalized-for-ecoinvent-v310.0fffd5e3daa5f4cf11ef83e49c375827.bw2package
regioinvent/data/IW/impact_world_plus_21_regionalized-for-ecoinvent-v39.af770e84bfd0f4365d509c026796639a.bw2package
regioinvent/data/ReCiPe/ReCiPe_regionalized-for-ecoinvent-v310.dd7e66b1994d898394e3acfbed8eef83.bw2package
regioinvent/data/ReCiPe/ReCiPe_regionalized-for-ecoinvent-v39.d03db1f1699b4f0b4d72626e52a40647.bw2package
regioinvent/data/Regionalization/ei3.10/COMTRADE_to_ecoinvent_geographies.json
regioinvent/data/Regionalization/ei3.10/COMTRADE_to_exiobase_geographies.json
regioinvent/data/Regionalization/ei3.10/HS_to_exiobase_name.json
regioinvent/data/Regionalization/ei3.10/country_to_ecoinvent_regions.json
regioinvent/data/Regionalization/ei3.10/ecoinvent_to_HS.json
regioinvent/data/Regionalization/ei3.10/electricity_aluminium_processes.json
regioinvent/data/Regionalization/ei3.10/electricity_processes.json
regioinvent/data/Regionalization/ei3.10/heat_industrial_ng_processes.json
regioinvent/data/Regionalization/ei3.10/heat_industrial_non_ng_processes.json
regioinvent/data/Regionalization/ei3.10/heat_small_scale_non_ng_processes.json
regioinvent/data/Regionalization/ei3.10/no_inputs_processes.json
regioinvent/data/Regionalization/ei3.10/relevant_non_traded_products.json
regioinvent/data/Regionalization/ei3.10/waste_processes.json
regioinvent/data/Regionalization/ei3.9/COMTRADE_to_ecoinvent_geographies.json
regioinvent/data/Regionalization/ei3.9/COMTRADE_to_exiobase_geographies.json
regioinvent/data/Regionalization/ei3.9/HS_to_exiobase_name.json
regioinvent/data/Regionalization/ei3.9/country_to_ecoinvent_regions.json
regioinvent/data/Regionalization/ei3.9/ecoinvent_to_HS.json
regioinvent-1.3.0.dist-info/licenses/LICENSE.md
regioinvent-1.3.0.dist-info/METADATA
regioinvent-1.3.0.dist-info/WHEEL
regioinvent-1.3.0.dist-info/top_level.txt
regioinvent-1.3.0.dist-info/RECORD
