Metadata-Version: 2.4
Name: regioinvent
Version: 1.3.0
Summary: Python class regionalizing processes from the ecoinvent database using trade date from the UN COMTRADE database and common sense.
Author-email: Maxime Agez <maxime.agez@polymtl.ca>
Maintainer-email: Maxime Agez <maxime.agez@polymtl.ca>
Project-URL: source, https://github.com/CIRAIG/Regioinvent/
Project-URL: homepage, https://github.com/CIRAIG/Regioinvent/
Project-URL: tracker, https://github.com/CIRAIG/Regioinvent/issues
Classifier: Development Status :: 4 - Beta
Classifier: Programming Language :: Python
Classifier: Programming Language :: Python :: 3
Classifier: Programming Language :: Python :: 3.9
Classifier: Programming Language :: Python :: 3.10
Classifier: Programming Language :: Python :: 3.11
Classifier: Programming Language :: Python :: 3.12
Classifier: Programming Language :: Python :: 3.13
Classifier: Natural Language :: English
Classifier: Operating System :: OS Independent
Classifier: Topic :: Scientific/Engineering
Requires-Python: ==3.11.8
License-File: LICENSE.md
Requires-Dist: brightway2
Requires-Dist: pandas
Requires-Dist: tqdm
Requires-Dist: wurst
Dynamic: license-file
